setup.py
hxq/__init__.py
hxq/db.py
hxq/httpx.py
hxq/main_module.py
hxq/my_log.py
hxq/win32.py
hxq.egg-info/PKG-INFO
hxq.egg-info/SOURCES.txt
hxq.egg-info/dependency_links.txt
hxq.egg-info/entry_points.txt
hxq.egg-info/requires.txt
hxq.egg-info/top_level.txt
hxq/libs/__init__.py
hxq/libs/win32_Excel.py
hxq/libs/db/__init__.py
hxq/libs/httpx/__init__.py
hxq/libs/httpx/chrome_agent.py
hxq/libs/httpx/http.py
hxq/libs/httpx/session.py
hxq/libs/win32/__init__.py
hxq/utils/__init__.py
hxq/utils/aes256.py
hxq/utils/common.py
hxq/utils/decorator.py
hxq/utils/encipher.py
hxq/utils/pic_code.py
hxq/utils/threadx.py